cpthook
