Metadata-Version: 1.1
Name: cpthook
Version: 1.0.1
Summary: Centrally manage hooks for git repositories
Home-page: https://github.com/aelse/cpthook
Author: Alexander Else
Author-email: aelse@else.id.au
License: BSD
Platform: UNKNOWN
Classifier: Development Status :: 4 - Beta
Classifier: Intended Audience :: Developers
Classifier: Intended Audience :: System Administrators
Classifier: License :: Other/Proprietary License
Classifier: Programming Language :: Python
Classifier: Programming Language :: Python :: 2.7
Classifier: Programming Language :: Python :: 3.3
Classifier: Topic :: Software Development
Classifier: Topic :: System :: Systems Administration
